{
  "todos": [
    {
      "is_done": true,
      "content": "434",
      "id": 1
    },
    {
      "is_done": true,
      "content": "?",
      "id": 2
    }
  ],
  "album": [
    {
      "category": false,
      "url": "434",
      "id": 1
    }
  ],
  "posts": [
    {
      "content": "잘보고 갑니다",
      "writer": "정형돈",
      "createdAt": "2025.01.14",
      "id": 1
    },
    {
      "content": "잘보고 갑니다2",
      "writer": "유재석",
      "createdAt": "2025.01.14",
      "id": 2
    },
    {
      "content": "잘보고 갑니다3",
      "writer": "정준하",
      "createdAt": "2025.01.14",
      "id": 3
    },
    {
      "content": "잘보고 갑니다4",
      "writer": "하하",
      "createdAt": "2025.01.14",
      "id": 4
    },
    {
      "content": "잘보고 갑니다5",
      "writer": "노홍철",
      "createdAt": "2025.01.14",
      "id": 5
    },
    {
      "content": "잘보고 갑니다4",
      "writer": "하하",
      "createdAt": "2025.01.14",
      "id": 6
    },
    {
      "content": "잘보고 갑니다4",
      "writer": "하하",
      "createdAt": "2025.01.14",
      "id": 7
    },
    {
      "content": "잘보고 갑니다4",
      "writer": "하하",
      "createdAt": "2025.01.14",
      "id": 8
    },
    {
      "content": "잘보고 갑니다4",
      "writer": "하하",
      "createdAt": "2025.01.14",
      "id": 9
    },
    {
      "writer": "test",
      "content": "This is the content of my first post1.",
      "createdAt": "2025.01.15",
      "id": 10
    },
    {
      "writer": "test",
      "content": "This is the content of my first post2.",
      "createdAt": "2025.01.15",
      "id": 11
    },
    {
      "writer": "test",
      "content": "This is the content of my first post3.",
      "createdAt": "2025.01.15",
      "id": 12
    },
    {
      "writer": "test",
      "content": "This is the content of my first post4.",
      "createdAt": "2025.01.15",
      "id": 13
    },
    {
      "writer": "test",
      "content": "This is the content of my first post5.",
      "createdAt": "2025.01.15",
      "id": 14
    },
    {
      "writer": "test",
      "content": "This is the content of my first post6.",
      "createdAt": "2025.01.15",
      "id": 15
    },
    {
      "writer": "test",
      "content": "This is the content of my first post7.",
      "createdAt": "2025.01.15",
      "id": 16
    },
    {
      "writer": "test",
      "content": "This is the content of my first post8.",
      "createdAt": "2025.01.15",
      "id": 17
    },
    {
      "writer": "test",
      "content": "This is the content of my first post9.",
      "createdAt": "2025.01.15",
      "id": 18
    },
    {
      "writer": "test",
      "content": "This is the content of my first post10.",
      "createdAt": "2025.01.15",
      "id": 19
    },
    {
      "writer": "test",
      "content": "This is the content of my first post11.",
      "createdAt": "2025.01.15",
      "id": 20
    },
    {
      "writer": "test",
      "content": "This is the content of my first post12.",
      "createdAt": "2025.01.15",
      "id": 21
    },
    {
      "writer": "test",
      "content": "This is the content of my first post13.",
      "createdAt": "2025.01.15",
      "id": 22
    },
    {
      "writer": "test",
      "content": "This is the content of my first post14.",
      "createdAt": "2025.01.15",
      "id": 23
    },
    {
      "writer": "test",
      "content": "This is the content of my first post15.",
      "createdAt": "2025.01.15",
      "id": 24
    },
    {
      "writer": "test",
      "content": "This is the content of my first post16.",
      "createdAt": "2025.01.15",
      "id": 25
    },
    {
      "writer": "test",
      "content": "This is the content of my first post17.",
      "createdAt": "2025.01.15",
      "id": 26
    },
    {
      "writer": "test",
      "content": "This is the content of my first post18.",
      "createdAt": "2025.01.15",
      "id": 27
    },
    {
      "writer": "test",
      "content": "This is the content of my first post19.",
      "createdAt": "2025.01.15",
      "id": 28
    },
    {
      "writer": "test",
      "content": "This is the content of my first post20.",
      "createdAt": "2025.01.15",
      "id": 29
    },
    {
      "writer": "test",
      "content": "This is the content of my first post21.",
      "createdAt": "2025.01.15",
      "id": 30
    },
    {
      "writer": "test",
      "content": "This is the content of my first post22.",
      "createdAt": "2025.01.15",
      "id": 31
    },
    {
      "writer": "test",
      "content": "This is the content of my first post23.",
      "createdAt": "2025.01.15",
      "id": 32
    },
    {
      "writer": "test",
      "content": "This is the content of my first post24.",
      "createdAt": "2025.01.15",
      "id": 33
    },
    {
      "writer": "test",
      "content": "This is the content of my first post25.",
      "createdAt": "2025.01.15",
      "id": 34
    },
    {
      "writer": "test",
      "content": "This is the content of my first post26.",
      "createdAt": "2025.01.15",
      "id": 35
    },
    {
      "writer": "test",
      "content": "This is the content of my first post27.",
      "createdAt": "2025.01.15",
      "id": 36
    },
    {
      "writer": "test",
      "content": "This is the content of my first post28.",
      "createdAt": "2025.01.15",
      "id": 37
    },
    {
      "writer": "test",
      "content": "This is the content of my first post29.",
      "createdAt": "2025.01.15",
      "id": 38
    },
    {
      "writer": "test",
      "content": "This is the content of my first post30.",
      "createdAt": "2025.01.15",
      "id": 39
    }
  ]
}
